LICENSE
README.md
setup.cfg
setup.py
importils/__init__.py
importils.egg-info/PKG-INFO
importils.egg-info/SOURCES.txt
importils.egg-info/dependency_links.txt
importils.egg-info/requires.txt
importils.egg-info/top_level.txt